[
    {
        "youtube": {
            "video_title": "How To Effortlessly Colour Your Hair At Home", 
            "video_id": "J5xNIJlfBAw", 
            "likes": 465.0, 
            "comments": 26.0, 
            "views": 57189.0
        }, 
        "facebook": {
            "views": 347175, 
            "video_id": 929871233757026, 
            "shares": 1254, 
            "likes": 5376, 
            "video_title": "How To Effortlessly Colour Your Hair At Home", 
            "comments": 476
        }, 
        "fb_yt": {
            "total_views": 404364.0, 
            "total_likes": 5841.0, 
            "total_comments": 502.0
        }
    }, 
    {
        "youtube": {
            "video_title": "Common \"Facts\" About Hair Colour Every Girl Should Know", 
            "video_id": "NlDWRmDCa_o", 
            "likes": 486.0, 
            "comments": 29.0, 
            "views": 28919.0
        }, 
        "facebook": {
            "views": 151550, 
            "video_id": 947482865329196, 
            "shares": 164, 
            "likes": 1344, 
            "video_title": "Everything You Need To Know About Hair Colour", 
            "comments": 81
        }, 
        "fb_yt": {
            "total_views": 180469.0, 
            "total_likes": 1830.0, 
            "total_comments": 110.0
        }
    }, 
    498725, 
    86108.0, 
    584833.0, 
    6720, 
    951.0, 
    7671.0, 
    557, 
    55.0, 
    612.0, 
    1418
]